[{"id":"11dfe60c33e74dbf","type":"tab","label":"NOP","disabled":false,"info":"","env":[]},{"id":"e497e7ed23d3da21","type":"nooperation","z":"11dfe60c33e74dbf","name":"","x":310,"y":160,"wires":[["eb410860b3782ff9","f16ae358cfcb6563"]]},{"id":"f83e26bc90c7c7d1","type":"inject","z":"11dfe60c33e74dbf","name":"","props":[{"p":"payload"}],"repeat":"","crontab":"","once":false,"onceDelay":0.1,"topic":"","payload":"first","payloadType":"str","x":150,"y":100,"wires":[["e497e7ed23d3da21"]]},{"id":"ca712d400367046b","type":"inject","z":"11dfe60c33e74dbf","name":"","props":[{"p":"payload"}],"repeat":"","crontab":"","once":false,"onceDelay":0.1,"topic":"","payload":"second","payloadType":"str","x":150,"y":160,"wires":[["e497e7ed23d3da21"]]},{"id":"25060b9c905cf241","type":"inject","z":"11dfe60c33e74dbf","name":"","props":[{"p":"payload"}],"repeat":"","crontab":"","once":false,"onceDelay":0.1,"topic":"","payload":"third","payloadType":"str","x":150,"y":220,"wires":[["e497e7ed23d3da21"]]},{"id":"f16ae358cfcb6563","type":"debug","z":"11dfe60c33e74dbf","name":"","active":true,"tosidebar":true,"console":false,"tostatus":false,"complete":"false","statusVal":"","statusType":"auto","x":490,"y":120,"wires":[]},{"id":"eb410860b3782ff9","type":"debug","z":"11dfe60c33e74dbf","name":"","active":true,"tosidebar":true,"console":false,"tostatus":false,"complete":"false","statusVal":"","statusType":"auto","x":490,"y":200,"wires":[]}]